classification_model/__init__.py
classification_model/config.yml
classification_model/pipeline.py
classification_model/predict.py
classification_model/train_pipeline.py
classification_model/datasets/__init__.py
classification_model/datasets/test.csv
classification_model/preprocessing/__init__.py
classification_model/preprocessing/data_manager.py
classification_model/preprocessing/features.py
classification_model/preprocessing/validation.py
classification_model/trained_models/__init__.py
classification_model/trained_models/titanic_classification_model_output_v0.0.1.pkl
tcm_model-0.0.1.dist-info/METADATA
tcm_model-0.0.1.dist-info/WHEEL
tcm_model-0.0.1.dist-info/top_level.txt
tcm_model-0.0.1.dist-info/RECORD
